[
  {
    "loop": 1,
    "story_id": "ANALYTICS-001",
    "error_message": "",
    "files_changed": 4,
    "timestamp": "2026-01-13T14:16:47+00:00"
  },
  {
    "loop": 2,
    "story_id": "ANALYTICS-002",
    "error_message": "",
    "files_changed": 2,
    "timestamp": "2026-01-13T14:22:50+00:00"
  },
  {
    "loop": 3,
    "story_id": "ANALYTICS-003",
    "error_message": "",
    "files_changed": 4,
    "timestamp": "2026-01-13T14:27:41+00:00"
  },
  {
    "loop": 4,
    "story_id": "ANALYTICS-004",
    "error_message": "",
    "files_changed": 2,
    "timestamp": "2026-01-13T14:31:34+00:00"
  },
  {
    "loop": 1,
    "story_id": "QUAL-001",
    "error_message": "",
    "files_changed": 6,
    "timestamp": "2026-01-14T00:57:16+00:00"
  },
  {
    "loop": 2,
    "story_id": "QUAL-002",
    "error_message": "",
    "files_changed": 8,
    "timestamp": "2026-01-14T01:37:35+00:00"
  },
  {
    "loop": 3,
    "story_id": "QUAL-004",
    "error_message": "",
    "files_changed": 6,
    "timestamp": "2026-01-14T02:15:10+00:00"
  },
  {
    "loop": 4,
    "story_id": "QUAL-005",
    "error_message": "",
    "files_changed": 8,
    "timestamp": "2026-01-14T02:20:47+00:00"
  },
  {
    "loop": 5,
    "story_id": "QUAL-006",
    "error_message": "",
    "files_changed": 8,
    "timestamp": "2026-01-14T02:27:11+00:00"
  },
  {
    "loop": 6,
    "story_id": "QUAL-007",
    "error_message": "",
    "files_changed": 6,
    "timestamp": "2026-01-14T02:32:52+00:00"
  },
  {
    "loop": 7,
    "story_id": "INT-001",
    "error_message": "",
    "files_changed": 8,
    "timestamp": "2026-01-14T02:38:53+00:00"
  },
  {
    "loop": 8,
    "story_id": "INT-002",
    "error_message": "",
    "files_changed": 8,
    "timestamp": "2026-01-14T02:43:53+00:00"
  },
  {
    "loop": 9,
    "story_id": "INT-003",
    "error_message": "",
    "files_changed": 8,
    "timestamp": "2026-01-14T02:50:55+00:00"
  },
  {
    "loop": 10,
    "story_id": "INT-004",
    "error_message": "",
    "files_changed": 6,
    "timestamp": "2026-01-14T02:57:11+00:00"
  },
  {
    "loop": 1,
    "story_id": "UX-016",
    "error_message": "",
    "files_changed": 5,
    "timestamp": "2026-01-15T15:24:22+01:00"
  },
  {
    "loop": 2,
    "story_id": "UX-017",
    "error_message": "",
    "files_changed": 7,
    "timestamp": "2026-01-15T15:25:59+01:00"
  },
  {
    "loop": 3,
    "story_id": "UX-018",
    "error_message": "",
    "files_changed": 7,
    "timestamp": "2026-01-15T15:28:28+01:00"
  },
  {
    "loop": 4,
    "story_id": "UX-019",
    "error_message": "",
    "files_changed": 7,
    "timestamp": "2026-01-15T15:30:43+01:00"
  },
  {
    "loop": 5,
    "story_id": "UX-020",
    "error_message": "",
    "files_changed": 7,
    "timestamp": "2026-01-15T15:32:52+01:00"
  },
  {
    "loop": 6,
    "story_id": "UX-021",
    "error_message": "",
    "files_changed": 7,
    "timestamp": "2026-01-15T15:35:05+01:00"
  },
  {
    "loop": 7,
    "story_id": "UX-022",
    "error_message": "",
    "files_changed": 7,
    "timestamp": "2026-01-15T15:39:40+01:00"
  },
  {
    "loop": 8,
    "story_id": "UX-023",
    "error_message": "",
    "files_changed": 7,
    "timestamp": "2026-01-15T15:42:34+01:00"
  },
  {
    "loop": 9,
    "story_id": "UX-024",
    "error_message": "",
    "files_changed": 7,
    "timestamp": "2026-01-15T16:16:54+01:00"
  },
  {
    "loop": 10,
    "story_id": "UX-026",
    "error_message": "",
    "files_changed": 3,
    "timestamp": "2026-01-15T16:19:17+01:00"
  },
  {
    "loop": 11,
    "story_id": "UX-027",
    "error_message": "",
    "files_changed": 7,
    "timestamp": "2026-01-15T16:52:51+01:00"
  },
  {
    "loop": 1,
    "story_id": "UX-017",
    "error_message": "",
    "files_changed": 7,
    "timestamp": "2026-01-16T00:18:29+01:00"
  },
  {
    "loop": 2,
    "story_id": "UX-018",
    "error_message": "",
    "files_changed": 9,
    "timestamp": "2026-01-16T00:22:07+01:00"
  },
  {
    "loop": 3,
    "story_id": "UX-019",
    "error_message": "",
    "files_changed": 3,
    "timestamp": "2026-01-16T00:26:10+01:00"
  },
  {
    "loop": 4,
    "story_id": "UX-020",
    "error_message": "",
    "files_changed": 7,
    "timestamp": "2026-01-16T00:29:56+01:00"
  },
  {
    "loop": 5,
    "story_id": "UX-021",
    "error_message": "",
    "files_changed": 6,
    "timestamp": "2026-01-16T00:33:27+01:00"
  },
  {
    "loop": 6,
    "story_id": "UX-022",
    "error_message": "",
    "files_changed": 7,
    "timestamp": "2026-01-16T00:37:45+01:00"
  },
  {
    "loop": 7,
    "story_id": "UX-023",
    "error_message": "",
    "files_changed": 3,
    "timestamp": "2026-01-16T00:41:14+01:00"
  },
  {
    "loop": 8,
    "story_id": "UX-024",
    "error_message": "",
    "files_changed": 7,
    "timestamp": "2026-01-16T00:44:24+01:00"
  },
  {
    "loop": 9,
    "story_id": "UX-025",
    "error_message": "",
    "files_changed": 3,
    "timestamp": "2026-01-16T00:48:14+01:00"
  },
  {
    "loop": 10,
    "story_id": "UX-026",
    "error_message": "",
    "files_changed": 2,
    "timestamp": "2026-01-16T00:51:52+01:00"
  },
  {
    "loop": 11,
    "story_id": "UX-027",
    "error_message": "",
    "files_changed": 3,
    "timestamp": "2026-01-16T00:55:25+01:00"
  },
  {
    "loop": 12,
    "story_id": "UX-028",
    "error_message": "",
    "files_changed": 7,
    "timestamp": "2026-01-16T00:58:58+01:00"
  },
  {
    "loop": 13,
    "story_id": "UX-029",
    "error_message": "",
    "files_changed": 7,
    "timestamp": "2026-01-16T01:01:17+01:00"
  },
  {
    "loop": 1,
    "story_id": "UX-030",
    "error_message": "",
    "files_changed": 6,
    "timestamp": "2026-01-16T09:01:17+01:00"
  },
  {
    "loop": 2,
    "story_id": "UX-031",
    "error_message": "",
    "files_changed": 7,
    "timestamp": "2026-01-16T09:03:52+01:00"
  },
  {
    "loop": 3,
    "story_id": "UX-032",
    "error_message": "",
    "files_changed": 7,
    "timestamp": "2026-01-16T09:06:01+01:00"
  },
  {
    "loop": 4,
    "story_id": "UX-033",
    "error_message": "",
    "files_changed": 7,
    "timestamp": "2026-01-16T09:08:59+01:00"
  },
  {
    "loop": 5,
    "story_id": "UX-034",
    "error_message": "",
    "files_changed": 7,
    "timestamp": "2026-01-16T09:11:11+01:00"
  },
  {
    "loop": 6,
    "story_id": "UX-035",
    "error_message": "",
    "files_changed": 7,
    "timestamp": "2026-01-16T09:13:45+01:00"
  },
  {
    "loop": 7,
    "story_id": "UX-036",
    "error_message": "",
    "files_changed": 3,
    "timestamp": "2026-01-16T09:16:59+01:00"
  }
]
